{
  "parent": "minecraft:recipes/root",
  "criteria": {
    "has_ender_pearl": {
      "conditions": {
        "items": [
          {
            "items": [
              "minecraft:ender_pearl"
            ]
          }
        ]
      },
      "trigger": "minecraft:inventory_changed"
    },
    "has_potion": {
      "conditions": {
        "items": [
          {
            "items": [
              "minecraft:potion"
            ]
          }
        ]
      },
      "trigger": "minecraft:inventory_changed"
    },
    "has_the_recipe": {
      "conditions": {
        "recipe": "minecraft:escape_potion"
      },
      "trigger": "minecraft:recipe_unlocked"
    }
  },
  "requirements": [
    [
      "has_the_recipe",
      "has_ender_pearl",
      "has_potion"
    ]
  ],
  "rewards": {
    "recipes": [
      "minecraft:escape_potion"
    ]
  },
  "sends_telemetry_event": false
}